requests_client/__init__.py
requests_client/__main__.py
requests_client/client.py
requests_client/config.py
requests_client/cursor_fetch.py
requests_client/exceptions.py
requests_client/fields.py
requests_client/lxml.py
requests_client/models.py
requests_client/schemas.py
requests_client/storage.py
requests_client/utils.py
requests_client-0.0.14.dist-info/METADATA
requests_client-0.0.14.dist-info/RECORD
requests_client-0.0.14.dist-info/WHEEL
requests_client-0.0.14.dist-info/top_level.txt
