Metadata-Version: 2.1
Name: requests-client
Version: 0.0.14
Summary: http://github.com/vgavro/requests-client
Home-page: http://github.com/vgavro/requests-client
Author: Victor Gavro
Author-email: vgavro@gmail.com
License: BSD
Platform: UNKNOWN
Classifier: Environment :: Web Environment
Classifier: Intended Audience :: Developers
Classifier: License :: OSI Approved :: BSD License
Classifier: Programming Language :: Python
Classifier: Topic :: Internet :: WWW/HTTP :: Dynamic Content
Classifier: Topic :: Software Development :: Libraries :: Python Modules
Requires-Dist: requests[socks] (>=2.13)
Requires-Dist: python-dateutil (>=2.7)
Requires-Dist: marshmallow (>=3.0.0rc1)
Requires-Dist: ipython
Requires-Dist: parso (>=0.1.1)
Requires-Dist: click
Requires-Dist: pdbpp
Requires-Dist: colorama
Requires-Dist: coloredlogs
Requires-Dist: pygments
Requires-Dist: requests-mock
Requires-Dist: pytest (>=3.8)
Requires-Dist: pytest-cov
Requires-Dist: pytest-flake8
Requires-Dist: pytest-variables[yaml]
